mum/__init__.py
mum/abstractsingleton.py
mum/noduplicates.py
mum/singleton.py
src/__init__.py
src/abstractsingleton.py
src/noduplicates.py
src/singleton.py
myusefulmetaclasses-0.0.7.dist-info/COPYING
myusefulmetaclasses-0.0.7.dist-info/METADATA
myusefulmetaclasses-0.0.7.dist-info/WHEEL
myusefulmetaclasses-0.0.7.dist-info/top_level.txt
myusefulmetaclasses-0.0.7.dist-info/RECORD
