Metadata-Version: 2.1
Name: myusefulmetaclasses
Version: 0.0.7
Summary: This is MUM: My Useful Metaclasses
Home-page: https://gitlab.com/kikulacho92/cruscoplanets
Author: Emiliano Minerba
Author-email: emi.nerba@gmail.com
License: GPL
Platform: UNKNOWN
Requires-Dist: wheel
